{
  "black": [
    {
      "content": "Alle Honoka-Figuren wurden aus der Vitrine gestohlen! Wen verdächtigt Levi zuerst? _.",
      "draw": 0,
      "pick": 1
    },
    {
      "content": "Levi hasst sehr viele Dinge, aber _ gehört nicht dazu.",
      "draw": 0,
      "pick": 1
    },
    {
      "content": "Umi sehnt sich nach einer Nacht voller _ zusammen mit Levi!",
      "draw": 0,
      "pick": 1
    },
    {
      "content": "Niemand kann Levi aufhalten, außer vielleicht _.",
      "draw": 0,
      "pick": 1
    },
    {
      "content": "_. Das kann man doch einfrieren.",
      "draw": 0,
      "pick": 1
    },
    {
      "content": "Chino möchte Levi verprügeln, weil er _ durch ihre Hintertür gelassen hat.",
      "draw": 0,
      "pick": 1
    },
    {
      "content": "_! Sie sind überall!",
      "draw": 0,
      "pick": 1
    },
    {
      "content": "_, Immer ein Genuss.",
      "draw": 0,
      "pick": 1
    },
    {
      "content": "Levis Lebensmotto: Wer einmal _ erlebt hat, hat alles gesehen.",
      "draw": 0,
      "pick": 1
    },
    {
      "content": "Erfolglos versucht Levi seinen Chef zu überzeugen, dass _ die Fernsehschrauben geklaut hat.",
      "draw": 0,
      "pick": 1
    },
    {
      "content": "Wenn der teuersten Rem-Figur in der Vitrine der Kopf fehlt, kann es nur einer gewesen sein: _!",
      "draw": 0,
      "pick": 1
    },
    {
      "content": "Sharo vereint Levis Meinung nach die Grundsätze von _ und _ in sich.",
      "draw": 1,
      "pick": 2
    },
    {
      "content": "Maki rollt unablässig über den Boden und Levi kann sie nur aufhalten, indem er _ freilässt.",
      "draw": 0,
      "pick": 1
    },
    {
      "content": "Kotori lebt ihren Traum. Levi lebt _.",
      "draw": 0,
      "pick": 1
    },
    {
      "content": "Bei Nikos Konzert bringt ihr Levi _ in die Garderobe.",
      "draw": 0,
      "pick": 1
    },
    {
      "content": "Ist das ein Vogel? Ist das Flugzeug? Nein, es ist _!",
      "draw": 0,
      "pick": 1
    },
    {
      "content": "Ich bin _, das kleine _. Hab scharfe Zähne, und davon ganz schön viel.",
      "draw": 1,
      "pick": 2
    },
    {
      "content": "Mehr _ braucht das Land!",
      "draw": 0,
      "pick": 1
    },
    {
      "content": "Wenn du glaubst, du hattest einen schlechten Tag, dann frag mal Levi. Ihm ist heute _ auf den Kopf gefallen.",
      "draw": 0,
      "pick": 1
    },
    {
      "content": "Jedes Mal, wenn sich Levi über _ aufregt, stirbt irgendwo auf der Welt _.",
      "draw": 1,
      "pick": 2
    },
    {
      "content": "Schritt 1: Levi. Schritt 2: _. Schritt 3: Profit.",
      "draw": 0,
      "pick": 1
    },
    {
      "content": "Ihr braucht nicht einkaufen! Wir haben noch _ im Gefrierschrank!",
      "draw": 0,
      "pick": 1
    },
    {
      "content": "Eine Umfrage ergab, dass 99 % aller Befragten Levi für _ halten.",
      "draw": 0,
      "pick": 1
    },
    {
      "content": "Wenn es sich Eri mal so richtig gut lassen möchte, zieht sie sich _ rein und denkt dabei an Levi.",
      "draw": 0,
      "pick": 1
    },
    {
      "content": "Levi konnte nach jahrelangen Selbstversuchen endlich das große Geheimnis um die Heilwirkung von _ lüften.",
      "draw": 0,
      "pick": 1
    },
    {
      "content": "_ ist tot. Wohin mit der Leiche?",
      "draw": 0,
      "pick": 1
    },
    {
      "content": "Wenn das Leben kein Ponyhof ist, dann ist Waldrems kein _.",
      "draw": 0,
      "pick": 1
    },
    {
      "content": "_. Vom LKW gefallen.",
      "draw": 0,
      "pick": 1
    },
    {
      "content": "Niemand kann Levi in Mario Cart schlagen, außer vielleicht _.",
      "draw": 0,
      "pick": 1
    },
    {
      "content": "Cocoa ist böse auf Levi, weil _.",
      "draw": 0,
      "pick": 1
    },
    {
      "content": "Chiya besteht auf Levis _!",
      "draw": 0,
      "pick": 1
    },
    {
      "content": "Von seinem ganzen Funi-Geld gönnt sich Levi erst mal _.",
      "draw": 0,
      "pick": 1
    },
    {
      "content": "\"Hast du noch mehr von _, das hat so schön geprickelt in meinem Bauchnabel?\"",
      "draw": 0,
      "pick": 1
    },
    {
      "content": "Levi hat weniger Shinys gefangen als Yaya. Was wirft er vor Frust durch die Gegend? _.",
      "draw": 0,
      "pick": 1
    },
    {
      "content": "_ in _. Empfohlen von Levi.",
      "draw": 1,
      "pick": 2
    },
    {
      "content": "Liebe ist was für Versager, Hass ist was für _.",
      "draw": 0,
      "pick": 1
    },
    {
      "content": "Nichts versüßt Levi mehr den Tag als _.",
      "draw": 0,
      "pick": 1
    },
    {
      "content": "Levi mag viele Dinge, aber _ gehört nicht dazu.",
      "draw": 0,
      "pick": 1
    },
    {
      "content": "Rem ist völlig von Levi enttäuscht, weil _.",
      "draw": 0,
      "pick": 1
    },
    {
      "content": "Für Nozomi steht eines fest! Levi ist ihr großer _!",
      "draw": 0,
      "pick": 1
    },
    {
      "content": "Mikan eskaliert auf dem Teppich. Wer oder was kann ihn jetzt noch aufhalten? _.",
      "draw": 0,
      "pick": 1
    },
    {
      "content": "Immer wenn du glaubst, niemand hat dich lieb, kommt _ vorbei und tritt dir in _.",
      "draw": 1,
      "pick": 2
    },
    {
      "content": "Levi reitet auf _ in den Sonnenuntergang.",
      "draw": 0,
      "pick": 1
    },
    {
      "content": "Wenn Levi sich etwas aussuchen könnte, dann wäre es ganz sicher _.",
      "draw": 0,
      "pick": 1
    },
    {
      "content": "Wenn Levi drei Dinge mit auf eine einsame Insel nehmen könnte, dann wäre _ auf jeden Fall dabei!",
      "draw": 0,
      "pick": 1
    },
    {
      "content": "_ am Morgen, vertreibt dem Levi Kummer und Sorgen.",
      "draw": 0,
      "pick": 1
    },
    {
      "content": "Rize ernährt sich ausschließlich von _. Levi findet das gut.",
      "draw": 0,
      "pick": 1
    },
    {
      "content": "Rin hält die Abstandsregeln nicht ein und wird von der indischen Polizei verprügelt. Levi eilt ihr zur Hilfe, indem er die Polizisten mit _ bewirft!",
      "draw": 0,
      "pick": 1
    },
    {
      "content": "\"Hast du schon mal von _ gehört? Levi hat mir das wärmstens empfohlen.\"",
      "draw": 0,
      "pick": 1
    },
    {
      "content": "Was ist die kleinste Brauerei Deutschlands? _.",
      "draw": 0,
      "pick": 1
    },
    {
      "content": "Levi zerstört den Preisständer auf der Arbeit. Dafür bekommt er  _.",
      "draw": 0,
      "pick": 1
    },
    {
      "content": "Was haben Levi und Hitler gemeinsam? _.",
      "draw": 0,
      "pick": 1
    },
    {
      "content": "_ ist schlimmer als Hitler. Levi ist schlimmer als _.",
      "draw": 1,
      "pick": 2
    }
  ],
  "white": [
    "Unsere hochverehrte Majestät, das Analoberhaupt.",
    "Rem.",
    "Rize.",
    "Tobis drölftausendstes Shiny, das er Levi unter die Nase reiben musste.",
    "Die Dorfassis von Waldrems.",
    "Häusliche Gewalt.",
    "Ein ganzer Kasten schales Bier.",
    "Ram.",
    "Cocoa.",
    "Dimbu.",
    "Mikan.",
    "Der Menschenschredder.",
    "Kirito.",
    "Chiya.",
    "So was.",
    "Yurio.",
    "Yoshi.",
    "Sharo.",
    "Schlechte Menschen.",
    "Yuri.",
    "Ein Ständer.",
    "Ein Tiefkühler.",
    "Unbändiges Stangenfieber.",
    "Eine Dose Hundefutter.",
    "Emilia.",
    "Eine Corona-Party.",
    "Ein Melonpan.",
    "Rem & Ram.",
    "Der Lappen.",
    "Kotori.",
    "Rin.",
    "Yaya.",
    "Fettsackschnappi.",
    "Eri.",
    "Haru.",
    "Ein sehr lang anhaltenden Ständer.",
    "Der Geiz der Schwaben.",
    "Eine Tüte voll dampfendem Hundekot.",
    "Ein bisschen Kleingeld in der Unterhose.",
    "Kotieren.",
    "Arschkrebs.",
    "Das Funimation-Schwarzgeld.",
    "Der Hund.",
    "Ein Monsterständer bis zum Mond.",
    "Tobi.",
    "Hanayo.",
    "Eine Brechstange tief im Nougatbunker.",
    "Eine Flasche alkoholfreies Bier.",
    "Umi.",
    "Michael.",
    "Levi.",
    "Ein Rudel Schwaben, das gerade ein Sonderangebot verpasst hat.",
    "Stuttgart 21.",
    "Niko.",
    "Nein.",
    "Kataschtrophe.",
    "Die PoGo-Spoofer.",
    "Schwuler Eiskunstlauf.",
    "Corona.",
    "Honoka.",
    "Ritter Ossi.",
    "Asuna.",
    "Katastrophe.",
    "Chino.",
    "Michael, Michael und Michael.",
    "Gyoza. Viele Gyoza.",
    "Maki.",
    "Christina.",
    "Der tollwütige Chihuahua von nebenan.",
    "Victor.",
    "Der VfB Stuttgart.",
    "Schackeline.",
    "Ein Rem-Dakimakura mit Körperöffnungen für mehr Spaß.",
    "Domenic.",
    "Nozomi.",
    "Mamas Reiseintopf aus der Tiefkühlung.",
    "Penis.",
    "Mamas Armee der Gefrierschränke.",
    "Eine Herde freilaufender Con-Creeps."
  ],
  "pack": {
    "id": "4KKZS",
    "name": "Cards Against Levi"
  },
  "quantity": {
    "black": 53,
    "white": 79,
    "total": 132
  },
  "dateStoredMs": 1588716333922
}