{
  "black": [
    {
      "content": "What will Greg Heffley be when he grows up? _",
      "draw": 0,
      "pick": 1
    },
    {
      "content": "What's more annoying than Manny Heffley? _",
      "draw": 0,
      "pick": 1
    },
    {
      "content": "Manny Heffley is a _",
      "draw": 0,
      "pick": 1
    },
    {
      "content": "Patty Ferrell had enough of Greg Heffley, so she _",
      "draw": 0,
      "pick": 1
    },
    {
      "content": "Manny Heffley killed _",
      "draw": 0,
      "pick": 1
    },
    {
      "content": "Where is the Heffley family's next location for their vacation? _",
      "draw": 0,
      "pick": 1
    },
    {
      "content": "Rowley Jefferson quit school to do _",
      "draw": 0,
      "pick": 1
    },
    {
      "content": "#NotMy_",
      "draw": 0,
      "pick": 1
    },
    {
      "content": "Rowley's new comic is called _",
      "draw": 0,
      "pick": 1
    },
    {
      "content": "Jeff Kinney's new, and very successful, book is called _",
      "draw": 0,
      "pick": 1
    },
    {
      "content": "Why did Susan and Frank Heffley fall out? _",
      "draw": 0,
      "pick": 1
    },
    {
      "content": "Diary of a Wimpy Kid: _",
      "draw": 0,
      "pick": 1
    },
    {
      "content": "What is Fregley's new fetish? _",
      "draw": 0,
      "pick": 1
    },
    {
      "content": "Frank and Susan Heffley get a divorce because _",
      "draw": 0,
      "pick": 1
    },
    {
      "content": "Greg Heffley and the _",
      "draw": 0,
      "pick": 1
    },
    {
      "content": "When Greg Heffley goes to school, what's the first thing he does to show everyone up? _",
      "draw": 0,
      "pick": 1
    },
    {
      "content": "Manny Heffley ruined Thanksgiving by doing _",
      "draw": 0,
      "pick": 1
    },
    {
      "content": "After the complete failure that was The Long Haul, Jeff Kinney decides that _ will be his new hobby.",
      "draw": 0,
      "pick": 1
    },
    {
      "content": "After falling out with Loded Diper, what is the name of Rodrick's new band? _",
      "draw": 0,
      "pick": 1
    }
  ],
  "white": [
    "#NotMyRodrick.",
    "POOPY.",
    "\"I'M NOT GAY, GREG!\".",
    "Chirag Gupta and the Guptas!.",
    "Fregley's disgusting stomach freckle.",
    "Bubby!.",
    "Diary of a Wimpy Kid: Greg Takes North Korea.",
    "\"I'm going to kill you.\".",
    "Loded Poopy Stinky McNasty Diper.",
    "Jeff Kinney: Ultimate Daddy.",
    "Diary of a Wimpy Kid: The Long Haul.",
    "Poopy Diper.",
    "Holly Hills.",
    "Greg Heffley and the Ballistic Missile.",
    "NUKE!.",
    "The Cheese Touch.",
    "Cartoon Susan Heffley looking forwards.",
    "Loded Diper.",
    "Jeff Kinney's book fetish.",
    "ZOO-WEE MAMA.",
    "Frank Heffley's secret stash of cocaine."
  ],
  "pack": {
    "id": "QFPRD",
    "name": "Diary of a Wimpy Kid"
  },
  "quantity": {
    "black": 19,
    "white": 21,
    "total": 40
  },
  "dateStoredMs": 1588537376141
}