{
  "black": [
    {
      "content": "Quand j’irai en prison, je cacherai _ dans mes fesses pour en faire la contrebande.",
      "draw": 0,
      "pick": 1
    },
    {
      "content": "À la Place des Arts ce mois-ci, la comédie musicale _.",
      "draw": 0,
      "pick": 1
    },
    {
      "content": "Qu’est-ce qui aide Harper à relaxer? _",
      "draw": 0,
      "pick": 1
    },
    {
      "content": "Résistance est _.",
      "draw": 0,
      "pick": 1
    },
    {
      "content": "Qu’est-ce qui me tient chaud pendant le long et froid hiver? _",
      "draw": 0,
      "pick": 1
    },
    {
      "content": "Vous n’avez pas vraiment vécu jusqu’à ce que vous expérimentiez _ et _ en même temps.",
      "draw": 1,
      "pick": 2
    },
    {
      "content": "Dans un monde ravagé par _, noter seul espoir est _.",
      "draw": 1,
      "pick": 2
    },
    {
      "content": "Qu’est-ce qui est le plus gay? _",
      "draw": 0,
      "pick": 1
    },
    {
      "content": "Le processus de guérison a commencé lorsque j’ai rejoint un groupe de soutien pour les victimes de _.",
      "draw": 0,
      "pick": 1
    },
    {
      "content": "Une étude démontre que des rats de laboratoire se déplacent deux fois plus vite après avoir été exposés à _.",
      "draw": 0,
      "pick": 1
    },
    {
      "content": "Quand je serai Premier Ministre, je créerai le ministère de _.",
      "draw": 0,
      "pick": 1
    },
    {
      "content": "Jésus est _.",
      "draw": 0,
      "pick": 1
    },
    {
      "content": "Qu’est-ce que Pauline Marois adore? _",
      "draw": 0,
      "pick": 1
    },
    {
      "content": "Je n’ai pas pardonné à George R. R. Martin depuis _.",
      "draw": 0,
      "pick": 1
    },
    {
      "content": "Qu’est-ce que le ministère des Transports interdit dorénavant sur tous les avions? _",
      "draw": 0,
      "pick": 1
    },
    {
      "content": "Devant le Pharaon impassible, Moïse provoqua la onzième plaie: _.",
      "draw": 0,
      "pick": 1
    },
    {
      "content": "J’ignore avec quelles armes se fera la Troisième Guerre mondiale, mais la Quatrième se fera avec _.",
      "draw": 0,
      "pick": 1
    },
    {
      "content": "Je bois pour oublier _.",
      "draw": 0,
      "pick": 1
    },
    {
      "content": "Qu’est-ce que j’ai rapporté du Mexique? _",
      "draw": 0,
      "pick": 1
    },
    {
      "content": "Qu’est-ce qui aide Barack Obama à se changer les idées? _",
      "draw": 0,
      "pick": 1
    },
    {
      "content": "Je n’arrive pas à croire qu’ils ont approuvé ma thèse de doctorat sur _.",
      "draw": 0,
      "pick": 1
    },
    {
      "content": "_. Impossible de s’en passer!",
      "draw": 0,
      "pick": 1
    },
    {
      "content": "Qu’est-ce que mes parents me cachent? _",
      "draw": 0,
      "pick": 1
    },
    {
      "content": "Étape 1: _. Étape 2: _. Étape 3: Profits.",
      "draw": 1,
      "pick": 2
    },
    {
      "content": "Quel est mon super-pouvoir secret? _",
      "draw": 0,
      "pick": 1
    },
    {
      "content": "C’est bien dommage de voir les enfants d’aujourd’hui avoir à dealer avec _.",
      "draw": 0,
      "pick": 1
    },
    {
      "content": "Avec assez de temps et d’énergie, _ va se transformer en _.",
      "draw": 1,
      "pick": 2
    },
    {
      "content": "Enfin, un service qui livre _ directement à la porte.",
      "draw": 0,
      "pick": 1
    },
    {
      "content": "Quel est le nouveau régime à la mode? _",
      "draw": 0,
      "pick": 1
    },
    {
      "content": "Le Biodôme présentera demain une nouvelle aire interactive portant sur _.",
      "draw": 0,
      "pick": 1
    },
    {
      "content": "Quand j’ai fait caca, qu’est-ce qui est sorti de mes fesses? _",
      "draw": 0,
      "pick": 1
    },
    {
      "content": "Quand j’étais sous acide, _ se transformait en _.",
      "draw": 1,
      "pick": 2
    },
    {
      "content": "_ est le nouveau _.",
      "draw": 1,
      "pick": 2
    },
    {
      "content": "Dans le septième cercle de l’enfer, les pécheurs doivent supporter _ pour l’éternité .",
      "draw": 0,
      "pick": 1
    },
    {
      "content": "Mon prof de gymnastique a été congédié pour avoir ajouté _ à la course à obstacles.",
      "draw": 0,
      "pick": 1
    },
    {
      "content": "Et l’Oscar pour _ est remis à _.",
      "draw": 1,
      "pick": 2
    },
    {
      "content": "Les vieux, ça sent quoi? _",
      "draw": 0,
      "pick": 1
    },
    {
      "content": "Qu’est-ce qui est le plus hardcore? _",
      "draw": 0,
      "pick": 1
    },
    {
      "content": "Qu’est-ce que les États-Unis ont parachuté aux enfants afghans? _",
      "draw": 0,
      "pick": 1
    },
    {
      "content": "La sortie scolaire a été totalement gâchée par _.",
      "draw": 0,
      "pick": 1
    },
    {
      "content": "Lors de relations sexuelles, j’aime penser à _.",
      "draw": 0,
      "pick": 1
    },
    {
      "content": "Chère Louise Deschâtelets, j’ai de la misère avec _, pouvez-vous m’aider?",
      "draw": 0,
      "pick": 1
    },
    {
      "content": "Pour mon prochain numéro, je vais faire sortir _ de _.",
      "draw": 1,
      "pick": 2
    },
    {
      "content": "Après avoir perdu connaissance au jour de l’an, j'ai été réveillé par _.",
      "draw": 0,
      "pick": 1
    },
    {
      "content": "Quel sera le prochain jouet dans les Happy Meal®? _",
      "draw": 0,
      "pick": 1
    },
    {
      "content": "_. C’est comme ça que je veux mourir.",
      "draw": 0,
      "pick": 1
    },
    {
      "content": "Quelle est la seule façon que je peux atteindre l’orgasme? _",
      "draw": 0,
      "pick": 1
    },
    {
      "content": "Quel est ta quête? _",
      "draw": 0,
      "pick": 1
    },
    {
      "content": "Internet est pour _.",
      "draw": 0,
      "pick": 1
    },
    {
      "content": "Je n’avais aucune idée que la chasse démon impliquerait autant de _.",
      "draw": 0,
      "pick": 1
    },
    {
      "content": "La guerre! Qu’est-ce que ça a de positif? _",
      "draw": 0,
      "pick": 1
    },
    {
      "content": "La science ne pourra jamais expliquer l’origine de _.",
      "draw": 0,
      "pick": 1
    },
    {
      "content": "Quand tout le reste échoue,, je peux toujours me masturber en pensant à _.",
      "draw": 0,
      "pick": 1
    },
    {
      "content": "Le Canal Vie présente _, la tragique histoire de _.",
      "draw": 1,
      "pick": 2
    },
    {
      "content": "Dans le nouveau film de Xavier Dolan, Roy Dupuis découvre que _ était en fait _ depuis le début.",
      "draw": 1,
      "pick": 2
    },
    {
      "content": "Pourquoi toutes ces carottes? Pourquoi les lapins ont besoin de cette bonne vision de toute manière? _",
      "draw": 0,
      "pick": 1
    },
    {
      "content": "À l’antenne de RDS, vous écoutez la Finale internationale de _.",
      "draw": 0,
      "pick": 1
    },
    {
      "content": "Le gouvernement socialiste de Scandinavie a déclaré que l’accès à _ est un droit humain fondamental.",
      "draw": 0,
      "pick": 1
    },
    {
      "content": "A Rome , il y a des rumeurs que le Vatican a une chambre secrète consacrée à _.",
      "draw": 0,
      "pick": 1
    },
    {
      "content": "Le prochain livre de J. K. Rowling: Harry Potter contre _.",
      "draw": 0,
      "pick": 1
    },
    {
      "content": "Je n’ai jamais compris _ jusqu’à ce que je connaisse _.",
      "draw": 1,
      "pick": 2
    },
    {
      "content": "Quel est le prochain duo de superhéros / acolyte? _ et _.",
      "draw": 1,
      "pick": 2
    },
    {
      "content": "Quel est le plaisir coupable de Batman? _",
      "draw": 0,
      "pick": 1
    },
    {
      "content": "Celui qui contrôle _ contrôle le monde.",
      "draw": 0,
      "pick": 1
    },
    {
      "content": "_. High five, le gros.",
      "draw": 0,
      "pick": 1
    },
    {
      "content": "Qu’est-ce qui a laissé cette tache sur mon divan? _",
      "draw": 0,
      "pick": 1
    },
    {
      "content": "Pendant le carême, de quoi vais-je me priver? _",
      "draw": 0,
      "pick": 1
    },
    {
      "content": "Le meilleur ami des filles, c’est _.",
      "draw": 0,
      "pick": 1
    },
    {
      "content": "Peut-être qu'elle est née avec. Peut-être que c’est _.",
      "draw": 0,
      "pick": 1
    },
    {
      "content": "Mais avant de vous tuer, M. Bond, je dois vous montrer _.",
      "draw": 0,
      "pick": 1
    },
    {
      "content": "Dans 1000 ans, l’argent papier ne sera qu’un vague souvenir, nous paierons les choses avec _.",
      "draw": 0,
      "pick": 1
    },
    {
      "content": "Désormais, le Père Noël n’apportera plus du charbon aux vilains enfants, mais _.",
      "draw": 0,
      "pick": 1
    },
    {
      "content": "_. C’est un piège!",
      "draw": 0,
      "pick": 1
    },
    {
      "content": "Des ethnographes ont récemment découvert une tribu aborigène vouant un culte à _.",
      "draw": 0,
      "pick": 1
    },
    {
      "content": "Dans un avenir lointain, les historiens seront d’accord que _ a marqué le début du déclin de l'Amérique.",
      "draw": 0,
      "pick": 1
    },
    {
      "content": "Quand je serai riche, je ferai ériger une statue de 15 mètres pour commémorer _.",
      "draw": 0,
      "pick": 1
    },
    {
      "content": "Ma vie est régie par un cycle vicieux de _ et _.",
      "draw": 1,
      "pick": 2
    },
    {
      "content": "Les extraterrestres ont refusé d’envahir la Terre pendant des années à cause de _.",
      "draw": 0,
      "pick": 1
    },
    {
      "content": "Les membres de l’élite paient des milliers de dollars juste pour expérimenter _.",
      "draw": 0,
      "pick": 1
    },
    {
      "content": "Qu’est-ce qui fait toujours lever le party? _",
      "draw": 0,
      "pick": 1
    },
    {
      "content": "La nouvelle téléréalité de TVA, c’est huit vedettes vieillissantes qui vivent avec _.",
      "draw": 0,
      "pick": 1
    },
    {
      "content": "Pourquoi ai-je des flatulences incontrôlables? _",
      "draw": 0,
      "pick": 1
    },
    {
      "content": "La Ligue nationale de hockey a banni _ à cause des avantages injustes que ça procure.",
      "draw": 0,
      "pick": 1
    },
    {
      "content": "La vie des Amérindiens fut changée à jamais lorsque l’Homme blanc lui apporta _.",
      "draw": 0,
      "pick": 1
    },
    {
      "content": "En un mot, _ peut être un substitut approprié pour _.",
      "draw": 1,
      "pick": 2
    },
    {
      "content": "Dans la ferme à Mathurin / Hi aïe hi aïe ho! / Y’a _. / Hi aïe hi aïe ho!",
      "draw": 0,
      "pick": 1
    },
    {
      "content": "_, ça mène toujours à _.",
      "draw": 1,
      "pick": 2
    },
    {
      "content": "_: Testé par les enfants, approuvé par les mamans.",
      "draw": 0,
      "pick": 1
    },
    {
      "content": "Les votes sont terminés, et la nouvelle mascotte de l’école est _.",
      "draw": 0,
      "pick": 1
    },
    {
      "content": "Vous seriez surpris de réaliser combien il y a de chevauchement dans un diagramme de Venn de _ et _.",
      "draw": 1,
      "pick": 2
    },
    {
      "content": "Qu’est-ce qu’on trouve par milliers au paradis? _",
      "draw": 0,
      "pick": 1
    },
    {
      "content": "J’ai rempli mon disque dur de photos de _.",
      "draw": 0,
      "pick": 1
    },
    {
      "content": "La «blind date» se déroulait horriblement jusqu’à ce que nous découvrions notre intérêt commun pour _.",
      "draw": 0,
      "pick": 1
    },
    {
      "content": "Pendant son enfance, Dalí a créé des centaines de tableaux représentant _.",
      "draw": 0,
      "pick": 1
    },
    {
      "content": "Qu’est-ce que grand-maman trouve d’abord perturbant, puis étrangement plaisant? _",
      "draw": 0,
      "pick": 1
    },
    {
      "content": "Qu’est-ce qui m’empêche de dormir? _",
      "draw": 0,
      "pick": 1
    },
    {
      "content": "Les blancs aiment bien _.",
      "draw": 0,
      "pick": 1
    },
    {
      "content": "Qu’est-ce qu’on brûle, hormis des sorcières? _",
      "draw": 0,
      "pick": 1
    },
    {
      "content": "Qu’est-ce qui a détruit ma dernière relation amoureuse? _",
      "draw": 0,
      "pick": 1
    },
    {
      "content": "Chaque Noël, mon oncle se saoule et raconte l'histoire de _.",
      "draw": 0,
      "pick": 1
    },
    {
      "content": "La dernière chose à laquelle pensa Michael Jackson avant de mourir fut _.",
      "draw": 0,
      "pick": 1
    },
    {
      "content": "_. Parce que je le mérite bien.",
      "draw": 0,
      "pick": 1
    },
    {
      "content": "Alors que les États-Unis et l’URSS s’affrontaient dans la course à l’espace, le Mexique dépensait des millions de pesos dans la recherche sur _.",
      "draw": 0,
      "pick": 1
    },
    {
      "content": "Qu’est-ce qui a rendu la vie difficile à la colonie de nudistes? _",
      "draw": 0,
      "pick": 1
    },
    {
      "content": "Des problèmes avec _? Essayez _!",
      "draw": 1,
      "pick": 2
    },
    {
      "content": "Je pensais avoir tout vu, jusqu’à ce que les extraterrestres nous montrent _.",
      "draw": 0,
      "pick": 1
    },
    {
      "content": "_: bon jusqu’à la dernière goutte.",
      "draw": 0,
      "pick": 1
    },
    {
      "content": "Dans le 24e siècle , tous les vaisseaux spatiaux seront équipés de _.",
      "draw": 0,
      "pick": 1
    },
    {
      "content": "Les derniers mots du capitaine furent: _.",
      "draw": 0,
      "pick": 1
    },
    {
      "content": "Qu’y a-t-il dans la boîte? _",
      "draw": 0,
      "pick": 1
    },
    {
      "content": "Pourquoi suis-je tout collant? _",
      "draw": 0,
      "pick": 1
    },
    {
      "content": "_. Génial en théorie, pas fameux en la pratique.",
      "draw": 0,
      "pick": 1
    },
    {
      "content": "Quand j’étais petit, j’adorais _.",
      "draw": 0,
      "pick": 1
    },
    {
      "content": "Qu’est-ce qui a mis fin à l’orgie? _",
      "draw": 0,
      "pick": 1
    },
    {
      "content": "Ma mère a paniqué quand elle a regardé mon historique de navigation et trouvé _.com.",
      "draw": 0,
      "pick": 1
    },
    {
      "content": "Agenouillez-vous devant _.",
      "draw": 0,
      "pick": 1
    },
    {
      "content": "À sa crise de la quarantaine, mon père s’est vraiment investi dans _.",
      "draw": 0,
      "pick": 1
    },
    {
      "content": "À Toronto, il est maintenant illégal de _.",
      "draw": 0,
      "pick": 1
    },
    {
      "content": "La meilleure/pire chose sur Tumblr est _.",
      "draw": 0,
      "pick": 1
    },
    {
      "content": "C'est une sorcière! Elle m'a transformé en _!",
      "draw": 0,
      "pick": 1
    },
    {
      "content": "Plus jamais de charades, depuis que ma mère a dû mimer _.",
      "draw": 0,
      "pick": 1
    },
    {
      "content": "Qu’est-ce que la Fondation du Dr Julien utilise pour aider les enfants pauvres à réussir? _",
      "draw": 0,
      "pick": 1
    },
    {
      "content": "C’est quoi ce son? _",
      "draw": 0,
      "pick": 1
    },
    {
      "content": "Je n’en peux plus d’avoir à expliquer _.",
      "draw": 0,
      "pick": 1
    },
    {
      "content": "Qu’est-ce que tu obtiens en multipliant six par neuf? _",
      "draw": 0,
      "pick": 1
    },
    {
      "content": "Tu dois être vraiment désespéré pour demander à _ de l'aide.",
      "draw": 0,
      "pick": 1
    },
    {
      "content": "Papa, pourquoi maman elle pleure? _",
      "draw": 0,
      "pick": 1
    },
    {
      "content": "Après le tremblement de terre, Céline Dion a donné _ aux habitants d’Haïti.",
      "draw": 0,
      "pick": 1
    },
    {
      "content": "C’est quoi cette nouvelle diète miracle? _",
      "draw": 0,
      "pick": 1
    },
    {
      "content": "Qu’est-ce que je ramène dans le passé pour convaincre tout le monde que je suis un sorcier puissant? _",
      "draw": 0,
      "pick": 1
    },
    {
      "content": "Qu’est-ce que Vin Diesel mange pour souper? _",
      "draw": 0,
      "pick": 1
    },
    {
      "content": "Mais qu’est-ce que ça sent? _",
      "draw": 0,
      "pick": 1
    },
    {
      "content": "_: c’est tellement emo!",
      "draw": 0,
      "pick": 1
    },
    {
      "content": "Un entretien d’embauche réussi commence par une poignée de main ferme et se termine par _.",
      "draw": 0,
      "pick": 1
    },
    {
      "content": "Nerds solitaires: Ne soyez plus solitaire, grâce à _!",
      "draw": 0,
      "pick": 1
    },
    {
      "content": "La vie était dure pour les hommes des cavernes avant _.",
      "draw": 0,
      "pick": 1
    },
    {
      "content": "_ + _ = _.",
      "draw": 2,
      "pick": 3
    },
    {
      "content": "Deux choses sont certaines dans la vie: la mort et _.",
      "draw": 0,
      "pick": 1
    },
    {
      "content": "Qu’est-ce qui me permet de ne plus toucher à la drogue? _",
      "draw": 0,
      "pick": 1
    },
    {
      "content": "C’est vrai, j’ai tué _. Avec _.",
      "draw": 1,
      "pick": 2
    },
    {
      "content": "La capacité de détruire une planète est insignifiante à côté de _.",
      "draw": 0,
      "pick": 1
    },
    {
      "content": "La meilleure chose à propos d’un nouvel ordinateur est _.",
      "draw": 0,
      "pick": 1
    },
    {
      "content": "La rumeur court que Vladimir Poutine adore manger _ fourré avec _.",
      "draw": 1,
      "pick": 2
    },
    {
      "content": "Qu’est-ce qui s’améliore avec le temps? _",
      "draw": 0,
      "pick": 1
    },
    {
      "content": "Je vis ma vie selon les enseignements de _.",
      "draw": 0,
      "pick": 1
    },
    {
      "content": "Qu’est-ce qui vous permet de coucher avec qui vous voulez? _",
      "draw": 0,
      "pick": 1
    },
    {
      "content": "Un romantique dîner aux chandelles ne serait pas une réussite sans _.",
      "draw": 0,
      "pick": 1
    },
    {
      "content": "Au clair de la lune / Mon ami Pierrot / Prête-moi _ / Pour _.",
      "draw": 1,
      "pick": 2
    },
    {
      "content": "Comment ai-je perdu ma virginité? _",
      "draw": 0,
      "pick": 1
    },
    {
      "content": "Voici la recette de ma vie amoureuse: _.",
      "draw": 0,
      "pick": 1
    },
    {
      "content": "_ a appelé. Il veut ravoir _.",
      "draw": 1,
      "pick": 2
    },
    {
      "content": "Un tribunal international a trouvé _ coupable de _.",
      "draw": 1,
      "pick": 2
    },
    {
      "content": "Personne ne croit que je suis vraiment allergique à _.",
      "draw": 0,
      "pick": 1
    },
    {
      "content": "Qu’est-ce que vous n’aimeriez pas trouver dans votre repas vietnamien? _",
      "draw": 0,
      "pick": 1
    },
    {
      "content": "C’est pas fa-ci-le / Quand _ te laisse tomber!",
      "draw": 0,
      "pick": 1
    },
    {
      "content": "Pourquoi est-ce que j’ai mal partout? _",
      "draw": 0,
      "pick": 1
    },
    {
      "content": "Mon prochain projet sera un modèle réduit de _.",
      "draw": 0,
      "pick": 1
    },
    {
      "content": "_, tout de même une histoire d’amour mieux que Twilight.",
      "draw": 0,
      "pick": 1
    },
    {
      "content": "Je m’excuse madame, je n’ai pas pu terminer mon devoir à cause de _.",
      "draw": 0,
      "pick": 1
    },
    {
      "content": "La règle 34 est toujours valide, sans exception, pas même pour _.",
      "draw": 0,
      "pick": 1
    },
    {
      "content": "Si Dieu ne voulait pas nous permettre d’apprécier _ il ne nous aurait pas donné _.",
      "draw": 1,
      "pick": 2
    },
    {
      "content": "Je ne suis peut-être pas bon dans les sports, mais je suis incroyable à _.",
      "draw": 0,
      "pick": 1
    },
    {
      "content": "Avant _, tout ce que nous avions, c’était _.",
      "draw": 1,
      "pick": 2
    },
    {
      "content": "La médecine reconnaît enfant les pouvoirs thérapeutiques de _.",
      "draw": 0,
      "pick": 1
    }
  ],
  "white": [
    "De la sauce Tabasco dans l’urètre.",
    "Être un sorcier, tabarnak!.",
    "L’oestrogène.",
    "Avoir des relations sexuelles sur une pizza.",
    "Un lion qui fait la baboune.",
    "Les chapeaux à hélices.",
    "Des cellules souches.",
    "Un tout petit cochon qui porte de toutes petites bottes de pluie.",
    "Les bélugas.",
    "Des robots volants qui tuent des gens.",
    "Le Télétubbie le plus gay des quatre.",
    "Du fromage fondu.",
    "Une glacière pleine d’organes.",
    "Penser roter et vomir par terre.",
    "Quelque chose qui peut tenir sur un «floppy disk» de 3.5”.",
    "Une énorme femme scandinave.",
    "Des implants cybernétiques.",
    "Cambrioler un zoo pour voler un singe.",
    "Le petit Jérémy.",
    "La brutalité policière.",
    "Un gars qui se liche les lèvres en te regardant.",
    "Une explosion de jus dans ma bouche.",
    "Une pitoune paquetée.",
    "Trouver Charlie.",
    "Les boulettes de viande du Ikea.",
    "Acheter les bons pantalons pour être cool.",
    "Une tribu de femmes guerrières.",
    "Le mariage, les enfants, le chalet, la retraite, la mort.",
    "Courir nu dans un centre d’achat en pissant et chiant partout.",
    "La cuisine mexicaine authentique.",
    "Échanger des plaisanteries.",
    "Gandhi.",
    "Les golden showers.",
    "Un pub irlandais.",
    "Une autre année de merde.",
    "Des préados.",
    "Un fusil à eau rempli de pisse de chat.",
    "Les femmes dans les pubs de yogourt.",
    "Des bébés morts.",
    "La douce revanche.",
    "Des déchets nucléaires.",
    "Des loups-garous.",
    "La peinture à numéros.",
    "L’espoir.",
    "Des crottes de nez.",
    "Un condom percé.",
    "Ma vie sexuelle.",
    "Le révérend Dr. Martin Luther King Jr.",
    "Dépenser beaucoup d’argent.",
    "Salut!.",
    "Des adultes se frappant l’un l’autre avec des épées rembourrées.",
    "Un AK-47.",
    "La Gendarmerie royale du Canada.",
    "La répression.",
    "Un mime qui fait un AVC.",
    "Les sans-abri.",
    "Être fabuleux.",
    "Jesus.",
    "L’abeille des Cheerios au miel et aux noix.",
    "Se piquer avec des seringues sales.",
    "Être en feu.",
    "Se faire pogner les culottes baissées, pour vrai.",
    "Porter des bobettes à l’envers pour ne pas faire de lavage.",
    "Mes parties génitales.",
    "Des enfants qui ont le cancer du cul.",
    "Vivre son homosexualité.",
    "Un meurtre crapuleux.",
    "Des préliminaires botchées.",
    "Des concours de beauté pour enfants.",
    "Passer une pierre aux reins.",
    "Des échantillons gratuits.",
    "Un régime de bananes.",
    "Faire l’amour tout en regardant «La liste de Schindler».",
    "Un livre ancien, plein de prophétie, à propos de toi.",
    "La porno sado-maso allemande.",
    "Cet endroit chaud et invitant entre l’anus et la poche.",
    "La peluche «Elmo chatouille-moi».",
    "Marcher sur un Lego.",
    "Jean Chréatien.",
    "Wikipedia.",
    "Un viol collectif.",
    "Violer, puis piller.",
    "Le laitier.",
    "Un paradoxe temporel.",
    "Pas les abeilles! Pas les abeilles!.",
    "Le Royaume du chocolat.",
    "Les Blancs.",
    "La folle au travail.",
    "Trois bébés et demi.",
    "Un prépuce.",
    "La révolte des Métis.",
    "Passe-Carreau.",
    "L’ouragan Katrina.",
    "Une tumeur au cerveau.",
    "La scène après le générique.",
    "Exactement ce qui devait arriver.",
    "L’herpès buccal.",
    "Cruiser les filles à la clinique d’avortement.",
    "Une production 100% nain de Richard III de Shakespeare.",
    "Des yogourts en tubes.",
    "Des castors volants qui fourrent.",
    "Des histoires érotiques avec Harry Potter.",
    "S’éloignant d’une explosion sans regarder en arrière.",
    "Les roux.",
    "La friction.",
    "Avoir les couilles bénites.",
    "L’évolution.",
    "La violence faite aux enfants.",
    "Un cheval avec une érection.",
    "Ne pas utiliser suffisamment de lubrifiant.",
    "La danse des canards.",
    "Une ado enceinte.",
    "Des pets de sang.",
    "Mahomet (Gloire à Lui).",
    "Ne pas porter de pantalons.",
    "Des gobelins.",
    "La violation du droit fondamental à la vie.",
    "Sa Majesté la reine Elizabeth II.",
    "Des saunas gais.",
    "Deux nains qui chient dans un sceau.",
    "Robert Downey Jr.",
    "Une pyramide de têtes coupées.",
    "Passer le doigt.",
    "Un cinquantenaire en patins à roulettes.",
    "Karine Vanasse.",
    "Le syndrome du bébé secoué.",
    "Un cul-de-jatte qui fait une crise d’épilepsie.",
    "Un Noël de paix et d’amour.",
    "Un poil pubien abandonné.",
    "L’économie.",
    "Être un dinosaure.",
    "Piller des tombes.",
    "L’attitude.",
    "L’alcoolisme.",
    "Détruire les pièces à conviction.",
    "Des émissions nocturnes.",
    "Des injections d’hormones.",
    "Barack Obama.",
    "La sélection naturelle.",
    "Un nettoyage ethnique.",
    "Une torsion testiculaire.",
    "La Scientologie.",
    "Tom Cruise.",
    "Un motel miteux.",
    "Des palourdes.",
    "Un paquet de Mentos et une bouteille de Coke Diète de deux litres.",
    "Les hommes.",
    "Une chaudière de têtes de poisson.",
    "Un vagin qui mène à une autre dimension.",
    "Jean «Là-Là» Tremblay.",
    "Des Post-il passif-agressifs.",
    "La preuve irréfutable de la vie sur Mars.",
    "S’asseoir pour faire pipi.",
    "Écoeurer des enfants.",
    "Le syndrome prémenstruel.",
    "Des oeufs de ptérodactyle.",
    "Lui torcher le cul.",
    "Les 10 mots inuits pour sperme.",
    "Une tortue vicieuse qui te mord la bite.",
    "Le placenta.",
    "Jouer à des jeux vidéo les fenêtres ouvertes, parce que c’est une belle journée.",
    "Un peu de temps juste pour moi.",
    "Des photos de seins.",
    "Le Ku Klux Klan.",
    "Les Français.",
    "L’odeur des vieux.",
    "Un foetus.",
    "Déflorer la princesse.",
    "72 vierges.",
    "Genghis Khan.",
    "Un moulin à vent rempli de cadavres.",
    "L’amour inconditionnel.",
    "Manger le dernier Bison connu.",
    "Éjecter un bébé aux neuf mois.",
    "Des chèvres qui mangent des sacs de poubelles.",
    "Staline.",
    "Un décolleté élégant.",
    "Manger un bonhomme de neige au complet.",
    "Youppi!.",
    "Les petits chanteurs du Mont-Royal.",
    "Des abeilles.",
    "Littéralement manger de la merde.",
    "Boire dix Red Bull pour avoir 50 heures d’énergie en continu.",
    "Des pandas qui copulent allègrement.",
    "Des abdominaux spectaculaires.",
    "Liberté et justice pour tous.",
    "Le Big Bang.",
    "Essayer de manger comme un être humain tout en portant un corset.",
    "Les chaînes de restaurant de banlieue.",
    "Ryan Gosling sur un cheval blanc.",
    "Envoyer des sextos.",
    "La violation des droits humains fondamentaux.",
    "Une douce caresse de l’entrejambe.",
    "Aller à l’église.",
    "Le solo de «My Heart Will Go On» au piccolo.",
    "La destruction mutuelle assurée.",
    "À l’infini.",
    "Une gigue endiablée.",
    "L’Immaculée Conception.",
    "Crier comme un fou.",
    "Mes démons intérieurs.",
    "Du velcro.",
    "L’Apocalypse.",
    "Des dommages collatéraux.",
    "Venir dans une flaque de larmes d’enfants.",
    "Sniffer de la colle.",
    "Guillaume Lemay-Thivierge.",
    "Plusieurs paires de lunettes.",
    "Voler des bébés.",
    "Un singe qui fume le cigare.",
    "Le clitoris.",
    "Rendre ça bizarre.",
    "La décence humaine.",
    "Un nain charmant.",
    "La folie des hommes.",
    "Michèle Richard.",
    "Des pantalons crissement serrés.",
    "Battre tes femmes.",
    "Galoper vers le soleil couchant.",
    "Une face à fesser d’dans.",
    "Des Stormtroopers.",
    "Des vieux Japonais.",
    "Mourir de la dysenterie.",
    "Des parents morts.",
    "Une surprise salée.",
    "Volts divisés par Ampère.",
    "Une lobotomie au pic à glace.",
    "La fondation Rêve d’Enfant.",
    "Le smegma.",
    "L’Association des scouts du Canada.",
    "Être violée par un orignal.",
    "Yodler quand c’est pas le temps.",
    "Branler un peu les fesses en signe de détresse.",
    "Des «flashbacks» du Vietnam.",
    "Le charisme.",
    "Agripper son sabre, saisir la corde et s’écrier: «À l’abordage!».",
    "Hulk Hogan.",
    "Une queue plus grande, plus noire.",
    "Boire comme un trou.",
    "Les féministes avec des poils faciaux.",
    "S’excuser.",
    "Les gars qui ne rappellent jamais.",
    "Sortir sa graine avec enthousiasme.",
    "Le rêve américain.",
    "Une dette accablante.",
    "Le soleil qui brille et les arcs-en-ciel.",
    "Des catapultes.",
    "Une belle personnalité.",
    "Jouer au Quidditch, pour de vrai.",
    "Une parade nuptiale.",
    "Des porn-stars.",
    "Le thon en conserve avec dauphin en plus.",
    "Une crotte qui sort et qui rentre.",
    "Un trombone rouillé.",
    "Les gais.",
    "Cruiser.",
    "Les Amish.",
    "Fumer un gros bat.",
    "Des centaures.",
    "Un perçage génital.",
    "L’écoute thérapeutique.",
    "Des chnolles.",
    "Le fruit défendu.",
    "Le cheval est une surprise.",
    "Une solitude indescriptible.",
    "Un avortement raté.",
    "Une présentation PowerPoint.",
    "La nécrophilie.",
    "Lancer une vierge dans un volcan.",
    "Des nones cochonnes.",
    "Pac-Man qui cale du sperme sans retenue.",
    "La déportation des Acadiens.",
    "La psychologie du développement.",
    "La Macarena.",
    "Des pancakes.",
    "Un micropénis.",
    "La vélocité d’une hirondelle égarée.",
    "Les cendres de grand-papa.",
    "Scalper.",
    "La tuerie de Polytechnique.",
    "Le talent d’actrice de Caroline Néron.",
    "Un spectacle de marionnettes.",
    "Internet dans son ensemble.",
    "La misère des riches.",
    "Ne pas contribuer à la société d’une manière significative.",
    "Des pensées suicidaires.",
    "Oublier de manger et en mourir.",
    "Être excité par légumes phalliques.",
    "Des Nazis.",
    "Les représentants du service à la clientèle.",
    "Supposer que toutes les personnes handicapées sont retardées.",
    "Des jumelles siamoises sexy.",
    "Faire la moue.",
    "CTRL-ALT-DEL.",
    "Du crystal meth.",
    "La paix dans le monde.",
    "Des pouces opposables.",
    "Arnold Schwarzenegger.",
    "Hubert Reeves.",
    "Lancer comme une fille.",
    "Un complexe d’Oedipe.",
    "Vomir mi-fellation.",
    "Des sécrétions vaginales.",
    "La ménopause.",
    "Une orgie de penguin.",
    "Un Tamagotchi négligé.",
    "Les producteurs de poulet de Bosnie.",
    "La lactation.",
    "Un chapeau vraiment très cool.",
    "Le gouffre humide et demandant de sa bouche.",
    "Les tétraplégiques.",
    "Un abonnement à Sentier Chasse et Pêche.",
    "La réhabilitation.",
    "Le vigilantisme.",
    "Les témoins de Jéhovah.",
    "Ne pas avoir de sexe.",
    "Se mettre tout nu et regarder Télétoon.",
    "Bob l’éponge.",
    "La combustion spontanée.",
    "Des sacrifices humains.",
    "L’équipe chinoise de gymnastique.",
    "Trois mois dans le trou.",
    "Séparer les eaux de la mer Rouge.",
    "Péter des yeules en sang.",
    "Un crayon bien aiguisé.",
    "Une occasion d’apprendre.",
    "La lèpre.",
    "Tous mes amis en train de mourir.",
    "Sucer des mecs dans une ruelle.",
    "Un dentiste sadique.",
    "Se pavaner.",
    "Se mettre en colère juste pour passer le temps.",
    "L’inévitable mort thermique de l’univers.",
    "Tricher aux Jeux olympiques spéciaux.",
    "Boire tout seul.",
    "Les terroristes.",
    "Un Taser.",
    "Se frotter subtilement sur quelqu’un.",
    "Touiller la salade.",
    "Des seins refaits tout croche.",
    "Une Bar-Mitzvah.",
    "Auschwitz.",
    "Rien.",
    "La drogue du viol.",
    "Les émotions.",
    "La destruction systématique de tout un peuple et de leur mode de vie.",
    "Fabriquer des statistiques.",
    "Laisser un message embarrassant sur le répondeur.",
    "L’amour intense de Nikola Tesla pour un pigeon.",
    "Des couvertures avec la variole.",
    "Les Noirs.",
    "Faire le bon choix.",
    "Être marginalisé.",
    "Ma collection de vibrateurs hi-tech.",
    "Justin Bieber.",
    "Jouer de la ruine-babines en fourrant une grosse truie dans la boîte d’un pickup.",
    "Des Pizza Pochettes.",
    "Une grosse quille de Wildcat tablette.",
    "Le tétanos.",
    "Nicolas Cage.",
    "Être extraordinaire.",
    "Une explosion thermonucléaire.",
    "Jacques Cartier.",
    "Un policier honnête qui n’a plus rien à perdre.",
    "Le lancer de nain sur une cible en velcro.",
    "Une critique nuancée.",
    "Le devoir conjugal.",
    "Atteindre rapidement l’orgasme.",
    "Des pantalons de cowboy qui laissent les fesses à l’air.",
    "Un party de saucisses.",
    "Faire l'amour à un mouton très sexy.",
    "Un anus blanchi.",
    "Un ninja aillant la diarrhée.",
    "De la viande de cheval.",
    "La raison.",
    "Un uppercut.",
    "Crier à la télévision parce que ça se passe différemment dans le livre .",
    "Godzilla.",
    "Des beaux pétards.",
    "Des sels de bain.",
    "Du sperme de baleine.",
    "Casse-Noisette.",
    "Des bouttes ben durs.",
    "Brûler en enfer.",
    "La tension sexuelle.",
    "Kanye West.",
    "Se décrasser le dessous des bourrelets.",
    "Une quantité surprenante de cheveux.",
    "Mourir.",
    "La méthode scientifique.",
    "Un condom troué.",
    "Un gif animé d’éjaculation faciale.",
    "La merveilleuse épopée de l’accouchement.",
    "Charles Tisseyre qui dit des cochonneries.",
    "Une vague imparable de fourmis de feu.",
    "Ne plus être capable de regarder son chien dans les yeux.",
    "Exister.",
    "Penser aux Hutus et aux Tutsis et trouver ça drôle.",
    "La prostate.",
    "Le SIDA.",
    "Remplir tous les orifices avec du pouding au caramel.",
    "Un dojo rival.",
    "Des victimes civiles.",
    "Apprendre à un robot à d’aimer.",
    "Xavier Dolan.",
    "Du Viagra.",
    "Un pet vaginal.",
    "Une antilope flatulente.",
    "Deux steamés, une patate frite.",
    "La Force.",
    "Des questions d’examen racistes.",
    "Mon âme.",
    "Une fille à papa.",
    "L’inceste.",
    "Des pilotes kamikazes.",
    "Une barre Mars frite et un verre de beurre fondu.",
    "BATMAN!!!.",
    "La bataille des plaines d’Abraham.",
    "Acheter des vêtements virtuels pour tes Sims plutôt que ta famille.",
    "Sexter accidentellement ta mère.",
    "Des problèmes intimes.",
    "Le droit de vote des femmes.",
    "Un petit déjeuner équilibré.",
    "Un trisomique très costaud.",
    "Du sexe surprise!.",
    "Les Vikings.",
    "Des mines antipersonnelles.",
    "Se retirer.",
    "Une piñata pleine de scorpions.",
    "L’offre et la demande.",
    "Du crastillon.",
    "Des jokes d’Holocauste au moment inopportun.",
    "Le Front de Libération du Québec.",
    "Une danse à 10.",
    "Donner son 110%.",
    "Des couches pleines de marde.",
    "Monsieur Net, juste derrière toi.",
    "Une belle grosse graine.",
    "Des accidents de chasse.",
    "Ta face.",
    "Des embuscades de velociraptors.",
    "Un pet sauce.",
    "Sean Connery.",
    "Hara-kiri.",
    "Une bonne claque su’a yeule.",
    "La minorité visible.",
    "Doigter.",
    "Cliquer frénétiquement sur des photos de chats sur Internet.",
    "Michael Jackson.",
    "Un montage de volleyball homoérotique.",
    "Renifler avec vigueur.",
    "La Bible.",
    "Du gâteau aux fruits.",
    "Les nanotechnologies.",
    "Un sac de fèves magiques.",
    "Les joueurs de djembé amateurs.",
    "Un amant Latino passionné.",
    "Un petit cheval.",
    "Des cuisses musclées.",
    "L’épisode de Noël.",
    "Ma machette.",
    "L’Alberta.",
    "Un «douche» avec une guitare acoustique.",
    "Un Calinours qui explique le sexe aux enfants.",
    "Une jeune noire plutôt coquine.",
    "Le Choeur de l’Armée Rouge.",
    "Fuck you.",
    "Être «unfriendé» sur Facebook.",
    "Violer les femmes et voler les chevaux.",
    "Toujours prendre des décisions niaiseuses.",
    "Les p’tits Éthiopiens.",
    "Grand-maman.",
    "L’esclavage.",
    "Le Stade olympique.",
    "Manger la moustache de Tom Selleck pour gagner ses pouvoirs.",
    "Des bobettes mangeables.",
    "Des petites culottes usagées.",
    "Des enfants tenus en laisse.",
    "Guérir l’homosexualité par la prière.",
    "Des oies.",
    "Gonfler Jeff Fillion à l’hélium et le regarder flotter vers l’horizon.",
    "Péter et s’en aller.",
    "Le sang du Christ.",
    "Un oncle raciste.",
    "Darth Vader.",
    "Rire des orphelins.",
    "Un hold-up dans une banque de sperme.",
    "Le dégoût de soi.",
    "Une feuille dans le vent.",
    "Manger un bébé phoque.",
    "Un démon avec un coeur en or.",
    "Les écologistes qui vivent dans les arbres.",
    "Le truc qui électrocute les abdominaux.",
    "Une pile de corps se tortillant.",
    "Ces moments où vous avez du sable dans le vagin.",
    "Des Asiatiques nuls en maths.",
    "Ta mère qui me demande en ami sur Facebook.",
    "Manger les meilleurs bonbons avant l’Halloween.",
    "Un coeur d’enfant.",
    "Des pédophiles.",
    "Faire un p’tit pipi.",
    "Nathalie Simard qui pleure en mangeant un p’tit pouding Laura Secord.",
    "Le vagin de Whoopi Goldberg.",
    "De la marde jusqu’au cou.",
    "Des boules anales.",
    "Être riche.",
    "Une pelletée de slotche.",
    "Couler un bronze.",
    "L’agriculture.",
    "De multiples coups de couteau.",
    "Des solos de saxophone.",
    "Se saouler au rince-bouche.",
    "55 gallons de lubrifiant.",
    "Se réveiller tout nu dans le stationnement d’un Valentine.",
    "Des orphelins qui te réchauffent le coeur.",
    "Les exercices pour stimuler l’esprit d’équipe en entreprise.",
    "Un autre osti de film de vampire.",
    "Bond. James Bond.",
    "L’autoflagellation.",
    "Les Juifs.",
    "Les critiques Amazon du balai vibrateur Nimbus 2000 d’Harry Potter.",
    "De mauvais choix de vie.",
    "Du fromage cottage.",
    "Éditer Wikipedia pour prouver un argument.",
    "Une branlette tristement exécutée.",
    "Un faucon de chasse.",
    "La musique New Age.",
    "Une érection qui dure plus que quatre heures.",
    "Des bébés chiens.",
    "Attendre jusqu’au mariage.",
    "Une scène de cul dans Lance et compte.",
    "L’abstinence.",
    "Fister.",
    "Le corps nu et huilé du Doc Mailloux.",
    "Un anneau pour les gouverner tous.",
    "Le caca qui brûle.",
    "Lécher de la bouffe pour que personne ne la prenne.",
    "Être second un dans concours de fellation.",
    "Se mettre tellement en colère que ça en donne une érection.",
    "Nourrir Ginette Reno.",
    "Cacher une érection.",
    "Du déodorant AXE.",
    "Stephen Hawking qui chuchote des obscénités.",
    "Des solutions synergétiques de gestion.",
    "L’orgasme féminin.",
    "Dieu.",
    "Faire des clins d’oeil à des vieux.",
    "Se faire des câlins.",
    "Des avortements au cintre.",
    "Des amputations à froid.",
    "Un environnement familial toxique.",
    "Faire semblant d’être intéressé.",
    "Se mettre à chanter et à danser.",
    "Les Amérindiens.",
    "Tripoter une plotte.",
    "Être bon au sexe.",
    "Des mangas pornos avec tentacules.",
    "Le système métrique.",
    "Souhaiter que des gobelins enlèvent votre petit frère.",
    "Mon statut marital.",
    "Le faire dans les fesses.",
    "Avoir tes règles pour la première fois.",
    "Une fête d’anniversaire ratée.",
    "Être seulement un peu enceinte.",
    "Le ping-pong de caca cul à cul.",
    "Laissant tomber tout le monde.",
    "Des Jos Louis.",
    "Plein de chats.",
    "Une malédiction gitane.",
    "Faire le zouave.",
    "Un onguent chinois 100% naturel.",
    "La famine.",
    "Beaucoup de bruit pour rien.",
    "Fantasmer sur les bûcherons.",
    "La science.",
    "Le sexe oral non réciproque.",
    "Souper avec votre ex.",
    "Enlever son chandail.",
    "La séduction.",
    "La section des commentaires.",
    "La stupidité la plus abjecte.",
    "Des crevettes à volonté pour 4,99$.",
    "La combustion spontanée.",
    "L’impuissance.",
    "Un hasard fou.",
    "La puberté.",
    "Les gentils Cubains.",
    "Du bling.",
    "Des rires en canne.",
    "Des travestis assez jolis merci.",
    "Des toilettes mixtes.",
    "Se promener les fesses à l’air.",
    "Des biscuits et des chatons.",
    "Se crisser du Tiers-Monde.",
    "Des armes de destructions massives.",
    "Une maudite tête de cochon.",
    "Des scies à chaînes comme mains.",
    "Faire ce qu’y a à faire.",
    "Des morceaux de prostituée en décomposition.",
    "Des sucettes géantes.",
    "Simple Plan.",
    "Gandalf.",
    "Assez d’héroïne pour tuer un éléphant.",
    "Du sperme d’elfe.",
    "«caller» l’orignal.",
    "Des sous-entendus discriminatoires.",
    "Ce cul.",
    "Des gratteux.",
    "La bactérie mangeuse de chair.",
    "Le testicule manquant de Lance Armstrong.",
    "Kim-Jong-il.",
    "Sniffer de la coke su’ l’cul d’une pute.",
    "René Angélil.",
    "Un criss de stool.",
    "Mourir seul dans la douleur.",
    "Des objets qui brillent.",
    "La poitrine légendaire de Mitsou.",
    "Rémy Girard.",
    "Se faire brouter la touffe.",
    "Le Pape.",
    "Une couverture médiatique.",
    "Stephen Harper.",
    "Un milliard de dollars.",
    "Personne ne sait.",
    "L’envie de pénis.",
    "Des batailles d’oreiller émoustillantes.",
    "Des amphétamines.",
    "De la soupe beaucoup trop chaude.",
    "Robocop.",
    "Des cicatrices purulentes d’épilation au laser.",
    "Des explosions.",
    "Les Résidences Soleil.",
    "Les licornes.",
    "L’obésité.",
    "Le caporal Lortie.",
    "L’autocannibalisme.",
    "Gambader.",
    "Douce, douce vengeance….",
    "Une vie pleine de tristesse.",
    "Une circoncision ratée.",
    "La masturbation.",
    "Une décharge électrique aux mamelons.",
    "Une possession démoniaque.",
    "Des fantômes.",
    "La cheerleader girl qui sauva le monde.",
    "Foncer dans l’tas.",
    "Mon vagin.",
    "Le silence.",
    "Des amputés.",
    "Britney Spears à 55 ans.",
    "Les pauvres.",
    "Gifler une vieille dame raciste.",
    "Jean Charest.",
    "Des ceintures de chasteté.",
    "Une piñata pleine de scorpions.",
    "Les Conservateurs.",
    "Tousser dans un vagin.",
    "Les filles qui textent toujours.",
    "Des camps de bûcherons.",
    "World of Warcraft.",
    "Don Cherry.",
    "Le racisme.",
    "Buzz Lightyear.",
    "L’accent du lac Saint-Jean.",
    "Une fellation au volant.",
    "Des enfants de chienne.",
    "Le Diable en personne.",
    "L’électricité.",
    "Appeler le Clan Panneton."
  ],
  "pack": {
    "id": "V4BA2",
    "name": "Quebec"
  },
  "quantity": {
    "black": 164,
    "white": 669,
    "total": 833
  },
  "dateStoredMs": 1588345344338
}